thermomave/__init__.py
thermomave/infer.py
thermomave/model.py
thermomave/post.py
thermomave/utils.py
thermomave-0.1.2.dist-info/WHEEL
thermomave-0.1.2.dist-info/METADATA
thermomave-0.1.2.dist-info/RECORD
