Metadata-Version: 2.1
Name: thermomave
Version: 0.1.2
Summary: 
Author: mahdikooshkbaghi
Author-email: mahdi.kooshkbaghi@gmail.com
Requires-Python: >=3.9,<4.0
Classifier: Programming Language :: Python :: 3
Classifier: Programming Language :: Python :: 3.10
Classifier: Programming Language :: Python :: 3.9
Requires-Dist: dill (>=0.3.4,<0.4.0)
Requires-Dist: numpyro (>=0.9.0,<0.10.0)
Requires-Dist: pandas (>=1.4.1,<2.0.0)
